code_review_mcp/__init__.py
code_review_mcp/cli.py
code_review_mcp/providers.py
code_review_mcp/py.typed
code_review_mcp/server.py
code_review_mcp/rules/code-review-en.mdc
code_review_mcp/rules/code-review.mdc
code_review_mcp-1.1.0.dist-info/METADATA
code_review_mcp-1.1.0.dist-info/WHEEL
code_review_mcp-1.1.0.dist-info/entry_points.txt
code_review_mcp-1.1.0.dist-info/licenses/LICENSE
code_review_mcp-1.1.0.dist-info/RECORD
