Metadata-Version: 2.4
Name: code-review-mcp
Version: 1.1.0
Summary: MCP Server for GitHub/GitLab code review - enables AI assistants to review pull requests and merge requests
Project-URL: Homepage, https://github.com/OldJii/code-review-mcp
Project-URL: Documentation, https://github.com/OldJii/code-review-mcp#readme
Project-URL: Repository, https://github.com/OldJii/code-review-mcp.git
Project-URL: Issues, https://github.com/OldJii/code-review-mcp/issues
Project-URL: Changelog, https://github.com/OldJii/code-review-mcp/blob/main/CHANGELOG.md
Author: Code Review MCP Contributors
Maintainer: Code Review MCP Contributors
License-Expression: MIT
License-File: LICENSE
Keywords: ai,claude,code-review,cursor,github,gitlab,mcp,merge-request,model-context-protocol,pull-request
Classifier: Development Status :: 4 - Beta
Classifier: Intended Audience :: Developers
Classifier: License :: OSI Approved :: MIT License
Classifier: Operating System :: OS Independent
Classifier: Programming Language :: Python :: 3
Classifier: Programming Language :: Python :: 3.10
Classifier: Programming Language :: Python :: 3.11
Classifier: Programming Language :: Python :: 3.12
Classifier: Programming Language :: Python :: 3.13
Classifier: Topic :: Software Development :: Quality Assurance
Classifier: Topic :: Software Development :: Version Control :: Git
Requires-Python: >=3.10
Requires-Dist: click>=8.0.0
Requires-Dist: httpx>=0.27.0
Requires-Dist: mcp>=1.0.0
Requires-Dist: pydantic>=2.0.0
Requires-Dist: starlette>=0.38.0
Requires-Dist: uvicorn>=0.30.0
Provides-Extra: dev
Requires-Dist: mypy>=1.10.0; extra == 'dev'
Requires-Dist: pytest-asyncio>=0.23.0; extra == 'dev'
Requires-Dist: pytest>=8.0.0; extra == 'dev'
Requires-Dist: ruff>=0.5.0; extra == 'dev'
